mysqlonsockets/__init__.py
mysqlonsockets/code.py
mysqlonsockets-0.0.1.dist-info/LICENSE.txt
mysqlonsockets-0.0.1.dist-info/METADATA
mysqlonsockets-0.0.1.dist-info/WHEEL
mysqlonsockets-0.0.1.dist-info/top_level.txt
mysqlonsockets-0.0.1.dist-info/RECORD
