Metadata-Version: 2.1
Name: mysqlonsockets
Version: 0.0.1
Summary: A module which helps you use your MYSQL database over local network by connecting another devices.
Author: Vedant Barhate
Author-email: vedant.barhate27@gmail.com
Keywords: python,socket,sockets,mysql,sql,database,server-client,sql remote user
Classifier: Development Status :: 1 - Planning
Classifier: Intended Audience :: Developers
Classifier: Programming Language :: Python :: 3
Classifier: Operating System :: Unix
Classifier: Operating System :: MacOS :: MacOS X
Classifier: Operating System :: Microsoft :: Windows
Classifier: License :: OSI Approved :: MIT License
License-File: LICENSE.txt
Requires-Dist: mysql.connector
Requires-Dist: datetime
